setup.py
scripts/tvguide
scripts/tvguide-csv
tvguide/__init__.py
tvguide/cartesian.f
tvguide/eclip.f
tvguide/getlun.f
tvguide/julian.f
tvguide/lentrim.f
tvguide/nutate.f
tvguide/sys.f
tvguide/tvguide.inc
tvguide/tvguide.py
tvguide/tvguide_minimal.f
tvguide/upcase.f
tvguide/version.py
tvguide.egg-info/PKG-INFO
tvguide.egg-info/SOURCES.txt
tvguide.egg-info/dependency_links.txt
tvguide.egg-info/top_level.txt